qr_code_engine/__init__.py
qr_code_engine/mainwindow.py
qr_code_engine/logic/__init__.py
qr_code_engine/logic/qrcodegenerator.py
qr_code_engine/subwindow/__init__.py
qr_code_engine/subwindow/multitextwindow.py
qr_code_engine-0.2.0.dist-info/METADATA
qr_code_engine-0.2.0.dist-info/WHEEL
qr_code_engine-0.2.0.dist-info/entry_points.txt
qr_code_engine-0.2.0.dist-info/license.txt
qr_code_engine-0.2.0.dist-info/top_level.txt
qr_code_engine-0.2.0.dist-info/RECORD
