Metadata-Version: 2.2
Name: qr_code_engine
Version: 0.2.0
Summary: This program helps to generate QR codes with a user interface
Author: Kuldeep Singh aka Aby
Author-email: shergillkuldeep@outlook.com
License: MIT
Classifier: Programming Language :: Python :: 3
Classifier: Programming Language :: Python :: 3.7
Classifier: License :: OSI Approved :: MIT License
Classifier: Operating System :: OS Independent
Requires-Python: >=3.6
License-File: license.txt
Requires-Dist: qrcode==8.0
Requires-Dist: Pillow==10.4.0
Requires-Dist: customtkinter==5.2.2
Requires-Dist: packaging
Dynamic: author
Dynamic: author-email
Dynamic: classifier
Dynamic: description
Dynamic: description-content-type
Dynamic: license
Dynamic: requires-dist
Dynamic: requires-python
Dynamic: summary
